Metadata-Version: 2.1
Name: beebird
Version: 0.1.0
Summary:  Task management and running platform for python 3
Home-page: https://github.com/randydu/beebird.git
Author: randydu
Author-email: randydu@gmail.com
License: MIT
Download-URL: https://github.com/randydu/beebird/archive/v0.1.0.tar.gz
Keywords: task,cmdlet
Platform: UNKNOWN
Classifier: Development Status :: 2 - Pre-Alpha
Classifier: Intended Audience :: Developers
Classifier: Operating System :: OS Independent
Classifier: Topic :: Software Development :: Libraries
Classifier: Topic :: Software Development :: Libraries :: Python Modules
Classifier: License :: OSI Approved :: MIT License
Classifier: Programming Language :: Python :: 3
